screenpy_adapter_allure/__init__.py
screenpy_adapter_allure/__version__.py
screenpy_adapter_allure/adapters.py
screenpy_adapter_allure-4.0.4.dist-info/LICENSE
screenpy_adapter_allure-4.0.4.dist-info/METADATA
screenpy_adapter_allure-4.0.4.dist-info/WHEEL
screenpy_adapter_allure-4.0.4.dist-info/RECORD
