Metadata-Version: 2.1
Name: screenpy-adapter-allure
Version: 4.0.4
Summary: An adapter for the microphone of ScreenPy's Narrator which sends logs to Allure.
Home-page: https://github.com/ScreenPyHQ/screenpy_adapter_allure
License: MIT
Author: Perry Goy
Author-email: perry.goy@gmail.com
Maintainer: Gabe Langton
Requires-Python: >=3.8,<4.0
Classifier: Development Status :: 5 - Production/Stable
Classifier: Intended Audience :: Developers
Classifier: License :: OSI Approved :: MIT License
Classifier: Natural Language :: English
Classifier: Operating System :: OS Independent
Classifier: Programming Language :: Python :: 3
Classifier: Programming Language :: Python :: 3.8
Classifier: Programming Language :: Python :: 3.9
Classifier: Programming Language :: Python :: 3.10
Classifier: Programming Language :: Python :: 3.11
Classifier: Programming Language :: Python :: 3 :: Only
Classifier: Topic :: Software Development :: Quality Assurance
Classifier: Topic :: Software Development :: Testing
Classifier: Topic :: Software Development :: Testing :: BDD
Provides-Extra: dev
Provides-Extra: dev-all
Provides-Extra: test
Requires-Dist: allure-pytest (>=2.13.1)
Requires-Dist: black ; extra == "dev-all"
Requires-Dist: coverage ; extra == "dev-all" or extra == "test"
Requires-Dist: flake8 ; extra == "dev-all"
Requires-Dist: importlib_metadata ; python_version >= "3.8.dev0" and python_version < "3.9.dev0"
Requires-Dist: isort ; extra == "dev-all"
Requires-Dist: mypy ; extra == "dev-all"
Requires-Dist: pre-commit ; extra == "dev" or extra == "dev-all"
Requires-Dist: pylint ; extra == "dev" or extra == "dev-all"
Requires-Dist: pytest ; extra == "dev" or extra == "dev-all" or extra == "test"
Requires-Dist: screenpy (>=4.0.2)
Requires-Dist: tox ; extra == "dev" or extra == "dev-all"
Project-URL: Documentation, https://screenpy-adapter-allure-docs.readthedocs.io/
Project-URL: Repository, https://github.com/ScreenPyHQ/screenpy_adapter_allure
